ut_ioc/__init__.py
ut_ioc/__version__.py
ut_ioc/csv_.py
ut_ioc/ioc.py
ut_ioc/jinja2_.py
ut_ioc/json_.py
ut_ioc/py.typed
ut_ioc/py_.py
ut_ioc/toml_.py
ut_ioc/yaml_.py
ut_ioc-2.0.0.20251020.dist-info/licenses/LICENSE.txt
ut_ioc-2.0.0.20251020.dist-info/METADATA
ut_ioc-2.0.0.20251020.dist-info/WHEEL
ut_ioc-2.0.0.20251020.dist-info/entry_points.txt
ut_ioc-2.0.0.20251020.dist-info/top_level.txt
ut_ioc-2.0.0.20251020.dist-info/RECORD
