Metadata-Version: 2.4
Name: ut_ioc
Version: 2.0.0.20251020
Summary: Utilities for IO Control
Author: Bernd Stroehle
Author-email: bernd.stroehle@gmail.com
Maintainer: Bernd Stroehle
Maintainer-email: bernd.stroehle@gmail.com
License-Expression: GPL-3.0-only WITH Classpath-exception-2.0 OR BSD-3-Clause
Project-URL: Source Code, https://github.com/bs29/ut_ioc/tree/master
Project-URL: Homepage, https://kosakya.de/
Project-URL: Documentation, https://ka-uts-uts.readthedocs.io/en/latest
Classifier: Development Status :: 5 - Production/Stable
Classifier: Intended Audience :: Developers
Classifier: Operating System :: OS Independent
Classifier: Programming Language :: Python :: 3.11
Classifier: Natural Language :: English
Classifier: Topic :: Software Development :: Libraries :: Python Modules
Requires-Python: >=3.10
License-File: LICENSE.txt
Requires-Dist: Jinja2>=3.1.6
Requires-Dist: orjson>=3.11.3
Requires-Dist: PyYAML>=6.0.3
Requires-Dist: rtoml>=0.12.0
Requires-Dist: toml>=0.10.2
Requires-Dist: ujson>=5.10.0
Requires-Dist: ut_dic>=1.5.2.20251008
Dynamic: license-file
